repoplone/__init__.py
repoplone/_types.py
repoplone/app.py
repoplone/cli.py
repoplone/distributions.py
repoplone/exceptions.py
repoplone/commands/__init__.py
repoplone/commands/changelog.py
repoplone/commands/release.py
repoplone/commands/settings.py
repoplone/commands/versions.py
repoplone/commands/dependencies/__init__.py
repoplone/settings/__init__.py
repoplone/settings/default.toml
repoplone/settings/parser.py
repoplone/utils/__init__.py
repoplone/utils/_git.py
repoplone/utils/_github.py
repoplone/utils/_hatch.py
repoplone/utils/_path.py
repoplone/utils/_requests.py
repoplone/utils/changelog.py
repoplone/utils/display.py
repoplone/utils/release.py
repoplone/utils/versions.py
repoplone/utils/dependencies/__init__.py
repoplone/utils/dependencies/constraints.py
repoplone/utils/dependencies/frontend.py
repoplone/utils/dependencies/pyproject.py
repoplone/utils/dependencies/versions.py
repoplone-1.0.0a7.dist-info/METADATA
repoplone-1.0.0a7.dist-info/WHEEL
repoplone-1.0.0a7.dist-info/entry_points.txt
repoplone-1.0.0a7.dist-info/RECORD
