Metadata-Version: 2.4
Name: RepoPlone
Version: 1.0.0a7
Summary: Toolset for Plone mono repo maintainers.
Project-URL: Documentation, https://github.com/plone/repoplone#readme
Project-URL: Issues, https://github.com/plone/repoplone/issues
Project-URL: Source, https://github.com/plone/repoplone
Author-email: kitconcept GmbH <info@kitconcept.com>, PloneGov-BR <gov@plone.org.br>
License-Expression: MIT
Keywords: Plone
Classifier: Development Status :: 3 - Alpha
Classifier: Environment :: Web Environment
Classifier: Framework :: Plone
Classifier: Framework :: Plone :: 6.1
Classifier: Intended Audience :: Developers
Classifier: License :: OSI Approved :: GNU General Public License v2 (GPLv2)
Classifier: Operating System :: OS Independent
Classifier: Programming Language :: Python
Classifier: Programming Language :: Python :: 3.12
Classifier: Programming Language :: Python :: 3.13
Requires-Python: >=3.12
Requires-Dist: dynaconf>=3.2.10
Requires-Dist: gitpython>=3.1.44
Requires-Dist: hatch>=1.14.0
Requires-Dist: hatchling>=1.27.0
Requires-Dist: mxdev>=4.0.3
Requires-Dist: packaging>=24.2
Requires-Dist: pyyaml>=6.0.2
Requires-Dist: requests>=2.32.3
Requires-Dist: semver>=3.0.4
Requires-Dist: tomlkit>=0.13.2
Requires-Dist: towncrier>=24.8.0
Requires-Dist: typer>=0.15.2
